braille_to_decimal.v
//KARKALA SRINIVASA VENKATARAMANA
//OM JAI DURGE MAA

module brailleToAscii(I,CLK,R,Y);
    input CLK;
    input R;
    input I;
    
    output [8:1] Y;

    reg [3:0] ps;
    reg [3:0] ns;
    reg [8:1] op;
    // string op;

    parameter [3:0] s0 = 0;
    parameter [3:0] s1 = 1;
    parameter [3:0] s2 = 2;
    parameter [3:0] s3 = 3;
    parameter [3:0] s4 = 4;
    parameter [3:0] s5 = 5;
    parameter [3:0] s6 = 6;
    parameter [3:0] s7 = 7;
    parameter [3:0] s8 = 8;
    parameter [3:0] s9 = 9;
    parameter [3:0] s10 = 10;
    parameter [3:0] s11 = 11;
    parameter [3:0] s12 = 12;

    always @(posedge CLK, R, I)
    begin
        if(~R) ps <= s0;
        else ps <= ns; //TODO: Check which one of blocking and non-blocking is more apt here
    end

    always @(ps, I)
    begin
        case(ps)
            s0: begin
                if(I) begin
                    ns = s0;
                    op = "";
                end
                else begin
                    ns = s1;
                    op = "";
                end
            end
            s1: begin
                if(I) begin
                    ns = s0;
                    op = "";
                end
                else begin
                    ns = s2;
                    op = "";
                end
            end
            s2: begin
                if(I) begin
                    ns = s3;
                    op = "";
                end
                else begin
                    ns = s4;
                    op = "";
                end
            end
            s3: begin
                if(I) begin
                    ns = s7;
                    op = "";
                end
                else begin
                    ns = s8;
                    op = null;
                end
            end
            s4: begin
                if(I) begin
                    ns = s5;
                    op = "";
                end
                else begin
                    ns = s0;
                    op = "";
                end
            end
            s5: begin
                if(I) begin
                    ns = s6;
                    op = "";
                end
                else begin
                    ns = s0;
                    op = "";
                end
            end
            s6: begin
                if(I) begin
                    ns = s0;
                    op = "0";
                end
                else begin
                    ns = s0;
                    op = "9";
                end
            end
            s7: begin
                if(I) begin
                    ns = s9;
                    op = "";
                end
                else begin
                    ns = s10;
                    op = "";
                end
            end
            s8: begin
                if(I) begin
                    ns = s12;
                    op = "";
                end
                else begin
                    ns = s11;
                    op = "";
                end
            end
            s9: begin
                if(I) begin
                    ns = s0;
                    op = "7";
                end
                else begin
                    ns = s0;
                    op = "6";
                end
            end
            s10: begin
                if(I) begin
                    ns = s0;
                    op = "4";
                end
                else begin
                    ns = s0;
                    op = "3";
                end
            end
            s11: begin
                if(I) begin
                    ns = s0;
                    op = "5";
                end
                else begin
                    ns = s0;
                    op = "1";
                end
            end
            s12: begin
                if(I) begin
                    ns = s0;
                    op = "8";
                end
                else begin
                    ns = s0;
                    op = "2";
                end
            end
        endcase
    end

    assign Y = op;
endmodule

testbench.v
//KARKALA SRINIVASA VENKATARAMANA
//OM JAI DURGE MAA

`timescale 1ns/1ns
`include "braille_to_decimal.v"

module brailleToBinaryTb();
    reg CLK;
    reg R;
    reg I;

    wire [8:1] Y;

    brailleToAscii BTA (I,CLK,R,Y);

    initial
    begin
        $dumpfile("braille_to_ascii.vcd");
        $dumpvars();
    end

    always
        #5 CLK = ~CLK;

    initial
    begin
        CLK = 1;

        R = 0; I = 0; #10;

        R = 1;
        I = 0; #10;
        I = 0; #10;
        I = 0; #10;
        I = 1; #10;
        I = 1; #10;
        I = 1; #10;
        I = 0; #10;
        I = 0; #10;
        I = 1; #10;
        I = 1; #10;
        I = 0; #10;
        I = 1; #10;
    end

    initial
    begin
        $display("Test Completed!!");
        #300 $finish;
    end
endmodule

braille_to_ascii.vcd
$date
	Mon Jan  9 22:00:16 2023
$end
$version
	Icarus Verilog
$end
$timescale
	1ns
$end
$scope module brailleToBinaryTb $end
$var wire 8 ! Y [8:1] $end
$var reg 1 " CLK $end
$var reg 1 # I $end
$var reg 1 $ R $end
$scope module BTA $end
$var wire 1 " CLK $end
$var wire 1 # I $end
$var wire 1 $ R $end
$var wire 8 % Y [8:1] $end
$var reg 4 & ns [3:0] $end
$var reg 8 ' op [8:1] $end
$var reg 4 ( ps [3:0] $end
$upscope $end
$upscope $end
$enddefinitions $end
#0
$dumpvars
b0 (
b0 '
b1 &
b0 %
0$
0#
1"
b0 !
$end
#5
0"
#10
b10 &
b1 (
1"
1$
#15
0"
#20
b100 &
b10 (
1"
#25
0"
#30
b0 &
b100 (
1"
#35
0"
#40
b0 (
b0 &
1"
1#
#45
0"
#50
1"
#55
0"
#60
1"
#65
0"
#70
b1 &
1"
0#
#75
0"
#80
b10 &
b1 (
1"
#85
0"
#90
b10 (
b11 &
1"
1#
#95
0"
#100
b111 &
b11 (
1"
#105
0"
#110
b111 (
b1010 &
1"
0#
#115
0"
#120
b110100 !
b110100 %
b110100 '
b1010 (
b0 &
1"
1#
#125
0"
#130
b0 !
b0 %
b0 '
b0 (
1"
